abu_color/__init__.py
abu_color/terminal_colors.py
abu_color-0.2.dist-info/METADATA
abu_color-0.2.dist-info/WHEEL
abu_color-0.2.dist-info/top_level.txt
abu_color-0.2.dist-info/RECORD
