Metadata-Version: 2.4
Name: abu_color
Version: 0.2
Summary: Terminal color formatter with foreground, background, and style support
Author: Abujelal Man
Classifier: Programming Language :: Python :: 3
Classifier: Environment :: Console
Classifier: Operating System :: OS Independent
Classifier: License :: OSI Approved :: MIT License
Requires-Python: >=3.6
Dynamic: author
Dynamic: classifier
Dynamic: description
Dynamic: description-content-type
Dynamic: requires-python
Dynamic: summary
